phonology_engine/__init__.py
phonology_engine/pe_native.py
phonology_engine/pe_output.py
phonology_engine/phonology_engine.py
phonology_engine/version.py
phonology_engine/Linux_x86/libPhonologyEngine.so
phonology_engine/Linux_x86_64/libPhonologyEngine.so
phonology_engine/Win32_x86/PhonologyEngine.dll
phonology_engine/Win64_x64/PhonologyEngine.dll
phonology_engine/tests/__init__.py
phonology_engine/tests/test_word_span.py
phonology_engine/tests/tests.py
phonology_engine-0.2.8.dist-info/LICENSE
phonology_engine-0.2.8.dist-info/METADATA
phonology_engine-0.2.8.dist-info/WHEEL
phonology_engine-0.2.8.dist-info/top_level.txt
phonology_engine-0.2.8.dist-info/RECORD
