Metadata-Version: 2.1
Name: phonology-engine
Version: 0.2.8
Summary: Module to get stress and syllables for words in a given sentence in Lithuanian language.
Home-page: https://github.com/aleksas/phonology_engine
Author: Aleksas Pielikis
Author-email: ant.kampo@gmail.com
License: BSD
Keywords: phonology_engine,phonology,pronunciation,stress,syllable,accent,hyphenation
Platform: UNKNOWN
Classifier: Intended Audience :: Developers
Classifier: License :: OSI Approved :: BSD License
Classifier: Natural Language :: English
Classifier: Programming Language :: Python
Classifier: Programming Language :: Python :: 2.7
Classifier: Programming Language :: Python :: 3
Classifier: Programming Language :: Python :: 3.4
